ail_typo_squatting/__init__.py
ail_typo_squatting/dns_local/resolving.py
ail_typo_squatting/etc/common-misspellings.json
ail_typo_squatting/etc/dynamic-dns.json
ail_typo_squatting/etc/homophones.txt
ail_typo_squatting/etc/tlds-alpha-by-domain.txt
ail_typo_squatting/format/output.py
ail_typo_squatting/format/regex.py
ail_typo_squatting/format/yaml.py
ail_typo_squatting/format/yara.py
ail_typo_squatting/generator/addDash.py
ail_typo_squatting/generator/addDynamicDns.py
ail_typo_squatting/generator/addTld.py
ail_typo_squatting/generator/addition.py
ail_typo_squatting/generator/changeDotDash.py
ail_typo_squatting/generator/changeOrder.py
ail_typo_squatting/generator/commonMisspelling.py
ail_typo_squatting/generator/const/main.py
ail_typo_squatting/generator/doubleReplacement.py
ail_typo_squatting/generator/homoglyph.py
ail_typo_squatting/generator/homophones.py
ail_typo_squatting/generator/missingDot.py
ail_typo_squatting/generator/numeralSwap.py
ail_typo_squatting/generator/omission.py
ail_typo_squatting/generator/repetition.py
ail_typo_squatting/generator/replacement.py
ail_typo_squatting/generator/singularPluralize.py
ail_typo_squatting/generator/stripDash.py
ail_typo_squatting/generator/subdomain.py
ail_typo_squatting/generator/utils/generator_functions.py
ail_typo_squatting/generator/utils/get_pathetc.py
ail_typo_squatting/generator/vowelSwap.py
ail_typo_squatting/generator/wrongSld.py
ail_typo_squatting/generator/wrongTld.py
ail_typo_squatting/typo.py
ail_typo_squatting/utils/parser.py
ail_typo_squatting-2.7.6.dist-info/LICENSE
ail_typo_squatting-2.7.6.dist-info/METADATA
ail_typo_squatting-2.7.6.dist-info/WHEEL
ail_typo_squatting-2.7.6.dist-info/entry_points.txt
ail_typo_squatting-2.7.6.dist-info/RECORD
