Metadata-Version: 2.3
Name: ail-typo-squatting
Version: 2.7.6
Summary: Generate list of domain name using Domain name permutation engine to feed AIL
License: BSD-2-Clause
Keywords: typo-squatting,typosquatting
Author: David Cruciani
Author-email: david.cruciani@circl.lu
Maintainer: Alexandre Dulaunoy
Maintainer-email: a@foo.be
Requires-Python: >=3.8,<4.0
Classifier: License :: OSI Approved :: BSD License
Classifier: Programming Language :: Python :: 3
Classifier: Programming Language :: Python :: 3.8
Classifier: Programming Language :: Python :: 3.9
Classifier: Programming Language :: Python :: 3.10
Classifier: Programming Language :: Python :: 3.11
Classifier: Programming Language :: Python :: 3.12
Classifier: Programming Language :: Python :: 3.13
Requires-Dist: dnspython (>=2.4.2,<3.0.0)
Requires-Dist: inflect (>=5.6.2,<6.0.0)
Requires-Dist: pyyaml (>=6.0.1,<7.0.0)
Requires-Dist: requests (>=2.31.0,<3.0.0)
Requires-Dist: retrie (>=0.2.4,<0.3.0)
Requires-Dist: tldextract (>=5.1.1,<6.0.0)
Project-URL: Repository, https://github.com/typosquatter/ail-typo-squatting
